magentic_olly/__init__.py
magentic_olly/details/__init__.py
magentic_olly/details/exporter/__init__.py
magentic_olly/details/exporter/ch_exporter.py
magentic_olly/details/exporter/filter_logs_exporter.py
magentic_olly/details/exporter/filter_spans_exporter.py
magentic_olly/details/initializer/__init__.py
magentic_olly/details/initializer/base.py
magentic_olly/details/initializer/logging.py
magentic_olly/details/initializer/provider.py
magentic_olly/details/initializer/tracing.py
magentic_olly/details/instrumentor/__init__.py
magentic_olly/details/instrumentor/event_bridge_instrumentor.py
magentic_olly/details/instrumentor/logging_instrumentor.py
magentic_olly/details/instrumentor/magentic_instrumentor.py
magentic_olly/details/model/__init__.py
magentic_olly/details/model/db_models.py
magentic_olly/details/model/model.py
magentic_olly/details/model/settings.py
magentic_olly/details/utils/__init__.py
magentic_olly/details/utils/constants.py
magentic_olly/details/utils/logger.py
magentic_olly/details/utils/spans.py
magentic_olly/details/utils/utils.py
magentic_olly/details/wrapper_params.py
magentic_olly/details/wrapper_service.py
magentic_olly/instrumentation.py
magentic_olly-0.2.1.dist-info/LICENSE
magentic_olly-0.2.1.dist-info/METADATA
magentic_olly-0.2.1.dist-info/WHEEL
magentic_olly-0.2.1.dist-info/RECORD
