Metadata-Version: 2.3
Name: magentic-olly
Version: 0.2.1
Summary: A package for custom opentelemetry instrumentation
License: MIT
Requires-Python: >=3.9,<4.0
Classifier: License :: OSI Approved :: MIT License
Classifier: Programming Language :: Python :: 3
Classifier: Programming Language :: Python :: 3.9
Classifier: Programming Language :: Python :: 3.10
Classifier: Programming Language :: Python :: 3.11
Classifier: Programming Language :: Python :: 3.12
Classifier: Programming Language :: Python :: 3.13
Requires-Dist: boto3
Requires-Dist: build (>=1.2.2.post1,<2.0.0)
Requires-Dist: httpx
Requires-Dist: opentelemetry-api (==1.29.0)
Requires-Dist: opentelemetry-exporter-otlp (==1.29.0)
Requires-Dist: opentelemetry-exporter-otlp-proto-grpc (==1.29.0)
Requires-Dist: opentelemetry-instrumentation-aws-lambda (==0.50b0)
Requires-Dist: opentelemetry-instrumentation-botocore (==0.50b0)
Requires-Dist: opentelemetry-instrumentation-httpx (==0.50b0)
Requires-Dist: opentelemetry-instrumentation-logging (==0.50b0)
Requires-Dist: opentelemetry-instrumentation-requests (==0.50b0)
Requires-Dist: opentelemetry-instrumentation-urllib (==0.50b0)
Requires-Dist: opentelemetry-sdk (==1.29.0)
Requires-Dist: pydantic (>=2.10.2,<3.0.0)
Requires-Dist: pydantic-core (>=2.27.1,<3.0.0)
Requires-Dist: pydantic-settings (>=2.6.1,<3.0.0)
Requires-Dist: requests
